{
  "_class": "shapePath",
  "booleanOperation": -1,
  "do_objectID": "3AC490C5-FAFA-4C39-9B29-459776F3FB47",
  "edited": true,
  "exportOptions": {
    "_class": "exportOptions",
    "do_objectID": "5137FB43-826C-4A3B-86FF-ADDE1B6CCCAD",
    "exportFormats": [
    ],
    "includedLayerIds": [
    ],
    "layerOptions": 0,
    "shouldTrim": false
  },
  "frame": {
    "_class": "rect",
    "constrainProportions": false,
    "do_objectID": "0B33B6C4-3291-43B1-AA45-D9E1B779BB42",
    "height": 2,
    "width": 512,
    "x": 0,
    "y": 158
  },
  "isClosed": false,
  "isFixedToViewport": false,
  "isFlippedHorizontal": false,
  "isFlippedVertical": false,
  "isLocked": false,
  "isVisible": true,
  "layerListExpandedType": 0,
  "name": "Line Copy 3",
  "nameIsFixed": false,
  "pointRadiusBehaviour": 0,
  "points": [
    {
      "_class": "curvePoint",
      "cornerRadius": 0,
      "curveFrom": "{0.0009765625, 0.75}",
      "curveMode": 1,
      "curveTo": "{0.0009765625, 0.75}",
      "hasCurveFrom": false,
      "hasCurveTo": false,
      "point": "{0, 0.5}"
    },
    {
      "_class": "curvePoint",
      "cornerRadius": 0,
      "curveFrom": "{0.95898437500000022, 0.5}",
      "curveMode": 1,
      "curveTo": "{0.95898437500000022, 0.5}",
      "hasCurveFrom": false,
      "hasCurveTo": false,
      "point": "{1, 0.5}"
    }
  ],
  "resizingConstraint": 63,
  "resizingType": 0,
  "rotation": 0,
  "shouldBreakMaskChain": false
}